parse_document_model/__init__.py
parse_document_model/attributes.py
parse_document_model/document.py
parse_document_model/marks.py
parse_document_model-0.2.2.dist-info/LICENSE
parse_document_model-0.2.2.dist-info/METADATA
parse_document_model-0.2.2.dist-info/WHEEL
parse_document_model-0.2.2.dist-info/top_level.txt
parse_document_model-0.2.2.dist-info/RECORD
