Metadata-Version: 2.1
Name: parse-document-model
Version: 0.2.2
Summary: Pydantic models for representing a text document as a hierarchical structure.
Home-page: https://github.com/OneOffTech/parse-document-model-python
Author: OneOffTech
Author-email: info@oneofftech.xyz
License: MIT
Project-URL: Source, https://github.com/OneOffTech/parse-document-model-python
Classifier: Intended Audience :: Developers
Classifier: License :: OSI Approved :: MIT License
Classifier: Programming Language :: Python
Classifier: Operating System :: OS Independent
Requires-Python: >=3.9
License-File: LICENSE
Requires-Dist: pydantic>=2.9.0
